bonsai/__init__.py
bonsai/seeds.py
bonsai/tune.py
bonsai/utils.py
bonsai/demo_configs/__init__.py
bonsai/demo_configs/catboost.yml
bonsai/demo_configs/lightgbm.yml
bonsai/demo_configs/xgboost.yml
bonsai_tree-1.2.dist-info/LICENSE
bonsai_tree-1.2.dist-info/METADATA
bonsai_tree-1.2.dist-info/WHEEL
bonsai_tree-1.2.dist-info/top_level.txt
bonsai_tree-1.2.dist-info/RECORD
