Metadata-Version: 2.1
Name: bonsai-tree
Version: 1.2
Summary: Bayesian Optimization + Gradient Boosted Trees
Home-page: https://github.com/magi-1/bonsai
Author: Landon Buechner
Author-email: mechior.magi@gmail.com
License: MIT
Platform: UNKNOWN
Classifier: Programming Language :: Python :: 3.6
Classifier: Programming Language :: Python :: 3.7
Classifier: Programming Language :: Python :: 3.8
Requires-Dist: xgboost (>=0.90)
Requires-Dist: catboost (>=0.26)
Requires-Dist: bayesian-optimization (>=1.2.0)
Requires-Dist: numpy (>=1.19.5)
Requires-Dist: pandas (>=1.1.5)
Requires-Dist: matplotlib (>=3.2.2)
Requires-Dist: seaborn (>=0.11.1)
Requires-Dist: plotly (>=4.4.1)
Requires-Dist: pyyaml (>=5.4.1)
